{
  "name": "CRIT_RING",
  "enabled": true,
  "spawning": {
    "biomes": [
      "BAMBOO_JUNGLE",
      "BAMBOO_JUNGLE_HILLS"
    ],
    "spawnDistance": 10.0,
    "randMultiplier": 0.5,
    "minY": 80,
    "maxY": 90,
    "shuffleLocations": true
  },
  "particle": {
    "particleName": "CRIT",
    "particleType": "RING",
    "maxCount": 7,
    "enableLighting": true
  },
  "properties": {
    "radius": 2,
    "rate": 0.4,
    "update": 5,
    "duration": 70,
    "rotationAngle": 0,
    "rotationAxis": "x"
  }
}